{
    "title": "Sesame-crusted Feta with black lime honey syrup",
    "blurb": "This dish is a little bit sweet, a lotta bit salty, a tiny bit bitter anda whole bit crispy.",
    "ingredients": [
        {
            "quantity": "2 blocks",
            "unit": "",
            "ingredient": "Greek feta",
            "preparation": "each cut into 4 triangles (8 triangles in total)"
        },
        {
            "quantity": "35g",
            "unit": "",
            "ingredient": "rice flour",
            "preparation": "(or plain flour if gluten-free flour not needed)"
        },
        {
            "quantity": "1",
            "unit": "large",
            "ingredient": "egg",
            "preparation": "well beaten"
        },
        {
            "quantity": "100g",
            "unit": "",
            "ingredient": "mixed black and white sesame seeds",
            "preparation": "lightly toasted"
        },
        {
            "quantity": "2",
            "unit": "tbsp",
            "ingredient": "olive oil",
            "preparation": ""
        },
        {
            "quantity": "2",
            "unit": "tbsp",
            "ingredient": "picked lemon thyme leaves",
            "preparation": "or regular thyme leaves"
        },
        {
            "quantity": "120g",
            "unit": "",
            "ingredient": "runny honey",
            "preparation": ""
        },
        {
            "quantity": "1",
            "unit": "tsp",
            "ingredient": "ground black lime",
            "preparation": "(p. 50) (optional)"
        },
        {
            "quantity": "3",
            "unit": "",
            "ingredient": "lemons",
            "preparation": "1 juiced to get 1 tbsp and the other 2 left whole"
        }
    ],
    "method": [
        "Line a shallow baking dish (or baking tray with a slight lip), about 30cm x 20cm in size, with baking parchment.",
        "Pat dry the feta pieces, then dip each piece in the flour, gently shaking off the excess. Coat in the egg, followed by the sesame seeds, making sure the feta pieces are completely coated. Transfer each piece to your prepared dish and refrigerate for at least 30 minutes, or longer if time allows.",
        "Preheat the oven to 220\u00b0C fan, Drizzle the coated feta pieces with the oil and bake from cold, for 18 minutes, very gently flipping the pieces over halfway, or until golden and warmed through.",
        "While the feta is baking, put the honey and black lime, if using, into a small saucepan on a medium-high heat. Once it starts to bubble, turn the heat to medium and cook, stirring occasionally, until it turns a deep amber caramel, about 6-7 minutes. Take off the heat and stir in the lemon juice. Set aside to cool for 5 minutes.",
        "Use a small, sharp knife to peel and segment the remaining two lemons and stir the segments into the cooled honey mixture.",
        "When ready, pour the lemon syrup directly over the feta in the baking dish, sprinkle with the thyme and serve at once, straight from the dish."
    ],
    "other": [
        "Prep time: 15 minutes",
        "Cook time: 30 minutes",
        "Chilling time: 30 minutes to overnight",
        "Serves 8",
        "Get ahead: Coat the feta the night before, cover well and keep refrigerated.",
        "Make it your own:",
        "~ Leave out the black lime as Special without it.",
        "if you can\u2019t find any \u2014 this dish is just as good.",
        "~ Swap out the feta for halloumi cheese instead"
    ]
}